pylint_blank_line_plugin/__init__.py
pylint_blank_line_plugin/blank_line.py
pylint_blank_line_plugin/checker.py
pylint_blank_line_plugin-0.1.4.dist-info/LICENSE
pylint_blank_line_plugin-0.1.4.dist-info/METADATA
pylint_blank_line_plugin-0.1.4.dist-info/WHEEL
pylint_blank_line_plugin-0.1.4.dist-info/RECORD
